minecraft_launcher_lib/__init__.py
minecraft_launcher_lib/_helper.py
minecraft_launcher_lib/command.py
minecraft_launcher_lib/exceptions.py
minecraft_launcher_lib/fabric.py
minecraft_launcher_lib/forge.py
minecraft_launcher_lib/install.py
minecraft_launcher_lib/java_utils.py
minecraft_launcher_lib/microsoft_account.py
minecraft_launcher_lib/microsoft_types.py
minecraft_launcher_lib/mrpack.py
minecraft_launcher_lib/natives.py
minecraft_launcher_lib/news.py
minecraft_launcher_lib/py.typed
minecraft_launcher_lib/quilt.py
minecraft_launcher_lib/runtime.py
minecraft_launcher_lib/types.py
minecraft_launcher_lib/utils.py
minecraft_launcher_lib/vanilla_launcher.py
minecraft_launcher_lib/version.txt
minecraft_launcher_lib/_internal_types/__init__.py
minecraft_launcher_lib/_internal_types/forge_types.py
minecraft_launcher_lib/_internal_types/helper_types.py
minecraft_launcher_lib/_internal_types/install_types.py
minecraft_launcher_lib/_internal_types/mrpack_types.py
minecraft_launcher_lib/_internal_types/runtime_types.py
minecraft_launcher_lib/_internal_types/shared_types.py
minecraft_launcher_lib/_internal_types/vanilla_launcher_types.py
minecraft_launcher_lib-7.0.dist-info/LICENSE
minecraft_launcher_lib-7.0.dist-info/METADATA
minecraft_launcher_lib-7.0.dist-info/WHEEL
minecraft_launcher_lib-7.0.dist-info/top_level.txt
minecraft_launcher_lib-7.0.dist-info/RECORD
