Metadata-Version: 2.1
Name: minecraft-launcher-lib
Version: 7.0
Summary: A library for creating a custom Minecraft launcher
Author-email: JakobDev <jakobdev@gmx.de>
License: BSD-2-Clause
Project-URL: Documentation, https://minecraft-launcher-lib.readthedocs.io/en/stable/index.html
Project-URL: Issues, https://codeberg.org/JakobDev/minecraft-launcher-lib/issues
Project-URL: Source, https://codeberg.org/JakobDev/minecraft-launcher-lib
Project-URL: Changelog, https://minecraft-launcher-lib.readthedocs.io/en/stable/changelog.html
Project-URL: Donation, https://ko-fi.com/jakobdev
Keywords: JakobDev,Minecraft,Mojang,launcher,minecraft-launcher,java
Classifier: Development Status :: 5 - Production/Stable
Classifier: Intended Audience :: Developers
Classifier: Environment :: Other Environment
Classifier: License :: OSI Approved :: BSD License
Classifier: Topic :: Games/Entertainment
Classifier: Operating System :: OS Independent
Classifier: Operating System :: POSIX
Classifier: Operating System :: POSIX :: BSD
Classifier: Operating System :: POSIX :: Linux
Classifier: Operating System :: MacOS :: MacOS X
Classifier: Operating System :: Microsoft :: Windows
Classifier: Programming Language :: Python :: 3
Classifier: Programming Language :: Python :: 3.10
Classifier: Programming Language :: Python :: 3.11
Classifier: Programming Language :: Python :: 3.12
Classifier: Programming Language :: Python :: 3.13
Classifier: Programming Language :: Python :: 3 :: Only
Classifier: Programming Language :: Python :: Implementation :: CPython
Classifier: Programming Language :: Python :: Implementation :: PyPy
Classifier: Typing :: Typed
Requires-Python: >=3.10
License-File: LICENSE
Requires-Dist: requests
